rtl/regfile.sv
// the special file where the outputs from the decoder are sent.

module regfile (
    input logic clk,
    input logic we, // safety switch write enable, 0 or 1.

    input logic [4:0] rs1, // decoder sends rs1 and rs2, the numbers CPU has to grab and send to ALU.
    input logic [4:0] rs2,
    input logic [4:0] rd, // recieved by the decoder
    input logic [31:0] wd, // comes from the ALU, is 32 bit. write data.
    output logic [31:0] rd1,
    output logic [31:0] rd2,
    output logic [31:0] dbg_x1,
    output logic [31:0] dbg_x2,
    output logic [31:0] dbg_x3
);

/* verilator lint_off EOFNEWLINE */
/* verilator lint_off PROCASSINIT */
/* verilator lint_off BLKSEQ */

    logic [31:0] regs [0:31]; // 32 registers, each 32 bits wide

    // 32'd0 = 32 bit wide decimal zero

    assign rd1 = (rs1 == 0) ? 32'd0 : regs[rs1]; // checks if the given register is zero, if yes, then it returns 32 bit wide zero, else it returns the value of the register.
    assign rd2 = (rs2 == 0) ? 32'd0 : regs[rs2];
    assign dbg_x1 = regs[1];
    assign dbg_x2 = regs[2];
    assign dbg_x3 = regs[3];

    always_ff @(posedge clk) begin // waiting for the clock, only then we right. so that the voltage gets on 1.
        if (we && rd != 0)
            regs[rd] <= wd;
    end

endmodule

rtl/alu.sv
module alu (
    input  logic [31:0] a,
    input  logic [31:0] b,
    input  logic [3:0]  alu_control,
    output logic [31:0] y
);

    always_comb begin 
        case (alu_control)

            4'b0000: y = a + b;
            4'b0001: y = a - b;
            4'b0010: y = a & b;
            4'b0011: y = a | b;
            4'b0100: y = a ^ b;
            4'b0101: y = a << b;
            4'b0110: y = a >> b;
            4'b0111: y = a >>> b;

            4'b1000: y = ($signed(a) <  $signed(b)) ? 32'd1 : 32'd0; // SLT
            4'b1001: y = ($signed(a) <= $signed(b)) ? 32'd1 : 32'd0;
            4'b1010: y = (a == b) ? 32'd1 : 32'd0; // EQ
            4'b1011: y = (a != b) ? 32'd1 : 32'd0;
            4'b1100: y = ($signed(a) >= $signed(b)) ? 32'd1 : 32'd0;
            4'b1101: y = ($signed(a) >  $signed(b)) ? 32'd1 : 32'd0; // GT

            default: y = 32'd0;

        endcase 
    end

endmodule

rtl/alu_control_unit.sv
module alu_control_unit (
    input  logic [1:0] alu_op,
    input  logic [2:0] funct3,
    input  logic [6:0] funct7,
    output logic [3:0] alu_control
);

    always_comb begin
        case (alu_op)
            2'b00: alu_control = 4'b0000; // add (loads/stores later)
            2'b01: alu_control = 4'b0001; // sub (branches later)

            2'b10: begin // R-type or I-type arithmetic
                case (funct3)
                    3'b000: alu_control = (funct7 == 7'b0100000) ? 4'b0001 : 4'b0000; // sub/add
                    3'b111: alu_control = 4'b0010; // and
                    3'b110: alu_control = 4'b0011; // or
                    3'b010: alu_control = 4'b1000; // SLT
                    3'b011: alu_control = 4'b1010; // EQ (custom mapping)

                    3'b100: alu_control = 4'b0100; // xor
                    3'b001: alu_control = 4'b0101; // sll
                    3'b101: alu_control = (funct7 == 7'b0100000) ? 4'b0111 : 4'b0110; // sra/srl
                    default: alu_control = 4'b0000;
                endcase
            end

            default: alu_control = 4'b0000;
        endcase
    end
endmodule

mem/dmem.sv
module dmem (
    input  logic        clk,
    input  logic        we,
    input  logic        re,
    input  logic [31:0] addr,
    input  logic [31:0] wd,
    input  logic [2:0]  funct3,
    output logic [31:0] rd,
    output logic misaligned
);

    /* verilator lint_off EOFNEWLINE */
    /* verilator lint_off CASEINCOMPLETE */
    /* verilator lint_off PROCASSINIT */
    /* verilator lint_off BLKSEQ */

    parameter RAM_SIZE = 4096;
    logic [1:0] mem_size; // 00 = byte, 01 = half, 10 = word
    logic mem_signed; // 1 = signed load, 0 = unsigned load
    logic [7:0] mem [0:RAM_SIZE-1];

    always_comb begin
        mem_size   = 2'b00;
        mem_signed = 1'b0;

        case (funct3)
            3'b000: mem_size = 2'b00; // LB / SB
            3'b001: mem_size = 2'b01; // LH / SH
            3'b010: mem_size = 2'b10; // LW / SW
            3'b100: mem_size = 2'b00; // LBU
            3'b101: mem_size = 2'b01; // LHU
        endcase

        if (re) begin
            case (funct3)
                3'b000, 3'b001, 3'b010: mem_signed = 1'b1; // LB/LH/LW
                default:                mem_signed = 1'b0; // LBU/LHU
            endcase
        end
    end 

    always_comb begin 
        misaligned = 1'b0;

        if (we || re) begin
            case (mem_size)
                2'b01: if (addr[0]   != 1'b0) misaligned = 1'b1;   // half
                2'b10: if (addr[1:0] != 2'b00) misaligned = 1'b1;  // word
                default: misaligned = 1'b0;                        // byte
            endcase
        end
    end


    always_ff @(posedge clk) begin
        if (we && !misaligned) begin
            case (mem_size)


                2'b00: begin // byte
                    mem[addr] <= wd[7:0];
                end

                2'b01: begin // half
                    mem[addr]     <= wd[7:0];
                    mem[addr + 1] <= wd[15:8];
                end

                2'b10: begin // word
                    mem[addr]     <= wd[7:0];
                    mem[addr + 1] <= wd[15:8];
                    mem[addr + 2] <= wd[23:16];
                    mem[addr + 3] <= wd[31:24];
                end

            endcase
        end
    end


    logic [31:0] load_data;

    always_comb begin
        load_data = 32'b0;

        case (mem_size)

            2'b00: load_data = {24'b0, mem[addr]};

            2'b01: load_data = {16'b0, mem[addr+1], mem[addr]};

            2'b10: load_data = {mem[addr+3], mem[addr+2],
                                mem[addr+1], mem[addr]};

        endcase
    end

    always_comb begin
        rd = 32'b0;

        if (re && !misaligned) begin
            case (mem_size)

                2'b00: rd = mem_signed ?
                            {{24{load_data[7]}},  load_data[7:0]}  :
                            {24'b0,               load_data[7:0]};

                2'b01: rd = mem_signed ?
                            {{16{load_data[15]}}, load_data[15:0]} :
                            {16'b0,               load_data[15:0]};

                2'b10: rd = load_data; // word always full 32 bits

            endcase
        end
    end

    endmodule

rtl/control_unit.sv
module control_unit  (
    input logic [6:0] opcode,
    output logic reg_we,
    output logic alu_src,
    output logic [1:0] alu_op,
    output logic mem_we,
    output logic mem_re,
    output logic mem_to_reg,
    output logic branch
    
);

    always_comb begin 
        mem_we = 0;
        mem_re = 0;
        mem_to_reg = 0;
        branch = 0;


        case (opcode) 
           7'b0110011: begin    // R-Type instruction
                reg_we = 1;
                alu_src = 0;
                alu_op = 2'b10; 
            end

            7'b1100111: begin // JALR
                reg_we = 1;
                alu_src = 1;
            end


            7'b1101111: begin // JAL
                reg_we = 1;
            end

            7'b1100011: begin // BRANCH
                alu_src = 0;
                alu_op  = 2'b01; // SUB
                branch  = 1;
            end

            7'b0010111: begin // AUIPC
                reg_we = 1;
                alu_src = 1;
                alu_op = 2'b00; // ADD
            end

            7'b0110111: begin // LUI
               reg_we = 1;
                alu_src = 1;
                alu_op = 2'b00; // ADD 
            end

            7'b0010011: begin // I-Type instruction
                reg_we = 1;
                alu_op = 2'b10;
                alu_src = 1;
            end

            7'b0000011: begin // LOAD WORD LW FROM DMEM
            reg_we = 1;
            alu_src = 1;
            alu_op  = 2'b00; // ADD for address
            mem_re = 1;
            mem_to_reg = 1;
            end

            7'b0100011: begin // STORE WORD SW FROM DMEM
                alu_src = 1;
                alu_op  = 2'b00; // ADD for address
                mem_we  = 1;
            end
        
            default: begin

            end
        endcase
    end

endmodule

rtl/imm_gen.sv
module imm_gen (
    input  logic [31:0] instr,
    output logic [31:0] imm
);

    logic [6:0] opcode;

    assign opcode = instr[6:0];

    always_comb begin
        case (opcode)

            // I-TYPE (addi, lw, jalr, etc.)
            7'b0010011,
            7'b0000011,
            7'b1100111:
                imm = {{20{instr[31]}}, instr[31:20]};

            // S-TYPE (sw)
            7'b0100011:
                imm = {{20{instr[31]}}, instr[31:25], instr[11:7]};

            // B-TYPE (beq, bne, etc.)
            7'b1100011:
                imm = {{19{instr[31]}},
                       instr[31],
                       instr[7],
                       instr[30:25],
                       instr[11:8],
                       1'b0};

            // U-TYPE (lui, auipc)
            7'b0110111,
            7'b0010111:
                imm = {instr[31:12], 12'b0};

            // J-TYPE (jal)
            7'b1101111:
                imm = {{11{instr[31]}},
                       instr[31],
                       instr[19:12],
                       instr[20],
                       instr[30:21],
                       1'b0};

            default:
                imm = 32'd0;

        endcase
    end

endmodule

rtl/decoder.sv
/*

    - Binary Decoder -

    Here the instruction is taken from the imem, that instruction is taken by the decoder and gets split in various sub-instructions.
    These sub-instructions are used to tell the CPU what to do, where to do and how to do. It returns various logics, one major 
    logic is a 7 bit opcode which is the type of instruction the CPU has to execute.

*/

module decoder (
    
    input logic [31:0] instr, // The output instruction which we sent from our memory module, ROM.
    output logic [6:0] opcode, // tells the CPU which type of instruction it is, 7 bits wide.
    output logic [4:0] rd, // the desintation register, the place where the result of the opcode instruction will be stored.
    output logic [4:0] rs1, // source register 1, the two numbers which CPU will grab to sent to the ALU.
    output logic [4:0] rs2, // source register 2
    output logic [2:0] funct3, // some extra bits used to distniguish further between instructions.
    output logic [6:0] funct7
   
);

/* verilator lint_off EOFNEWLINE */
/* verilator lint_off PROCASSINIT */
/* verilator lint_off BLKSEQ */ 

// this part splits the instruction.
// lets say, the instr is 000000 00010 00001 000 00011 0110011
// opcode = 0110011
// rd = 00011
// funct3 = 000
// rs1 = 00001
// rs2 = 00010
// funct7 = 000000

    assign opcode = instr[6:0];
    assign rd = instr[11:7];
    assign funct3 = instr[14:12];
    assign rs1 = instr[19:15];
    assign rs2 = instr[24:20];
    assign funct7 = instr[31:25];


endmodule

rtl/instruction_input_memory.sv
// handles the program which has to run

module instruction_input_memory (
    input logic [31:0] addr, // the address of the instruction
    output logic [31:0] instr // the 32 bit instruction, which is returned
);

    logic [31:0] mem [0:255]; // this is the storage of memory, has 256 slots, and each slot is 32 bits wide. It can hold 256 instructions.

    initial begin
        mem[0] = 32'h00500093; // addi x1, x0, 5
        mem[1] = 32'h008002EF; // jal  x5, func (pc+8)
        mem[2] = 32'h0000006F; // jal  x0, 0 (loop forever)
        mem[3] = 32'h00A08093; // addi x1, x1, 10
        mem[4] = 32'h00028067; // jalr x0, x5, 0 (return)
    end


    // in 32 bit systems, instructions are 4 bytes long, so each instruction takes 4 bytes. here mem[0] is on address 0, but mem[1] is on address 4 and mem[2] is on address 8.
    // so as the instruction is 4 bytes long, the end of it's binary address is with 00. so we're simply stripping off the last two 0s in this code.
    // this simply divides the address by 4. This is the bit shift, shifting right side by two places.
    // 9 is the ceiling because from n power of 2, the maximum it could go is 8. 8 bits, but only for the 256 slots we assigned.
    assign instr = mem[addr[9:2]]; // finally assigning the output instruction which was 32 bits wide, 

endmodule

rtl/cpu_top.sv
module cpu_top (
    input  logic clk,
    input  logic reset,
    output logic [31:0] pc_dbg,
    output logic [31:0] dbg_x1,
    output logic [31:0] dbg_x2,
    output logic [31:0] dbg_x3
);

/* verilator lint_off BLKSEQ */
    logic alu_src;
logic [1:0] alu_op;
    logic [31:0] alu_b;
    logic [3:0] alu_control;
    logic [31:0] pc; // program counter
    logic [31:0] instr; // instructions
    assign pc_dbg = pc;
    logic [6:0] opcode; // type of instruction
    logic [4:0] rd, rs1, rs2;// the register destination and sources
    logic [2:0] funct3; // extra bits to distinguish between instructions
    logic [6:0] funct7; // extra bits to distinguish between instructions
    logic mem_we, mem_re, mem_to_reg;
    logic [31:0] mem_data;
logic branch;
logic branch_taken;
logic [31:0] branch_target;



    integer cycle = 0;

    function string alu_op_name(input logic [3:0] ctrl);
        case (ctrl)
            4'b0000: alu_op_name = "ADD";
            4'b0001: alu_op_name = "SUB";
            4'b0010: alu_op_name = "AND";
            4'b0011: alu_op_name = "OR";
            4'b0100: alu_op_name = "XOR";
            4'b0101: alu_op_name = "SLL";
            4'b0110: alu_op_name = "SRL";
            4'b0111: alu_op_name = "SRA";
            4'b1000: alu_op_name = "SLT";
            4'b1001: alu_op_name = "SLTU";
            default: alu_op_name = "UNKNOWN";
        endcase
    endfunction

pc pc_u (
    .clk(clk),
    .reset(reset),
    .branch_taken(branch_taken),
    .branch_target(branch_target),
    .pc_out(pc)
);


    instruction_input_memory imem_u (
        .addr(pc), 
        .instr(instr) // returns 000000 00010 00001 000 00011 0110011
    );

    decoder dec_u (
        .instr(instr),
        .opcode(opcode),
        .rd(rd),
        .rs1(rs1),
        .rs2(rs2),
        .funct3(funct3),
        .funct7(funct7)
    );

    logic [31:0] imm;

    imm_gen imm_u (
        .instr(instr),
        .imm(imm)
    );

    logic jal;
    assign jal = (opcode == 7'b1101111);

    logic jalr;
    assign jalr = (opcode == 7'b1100111);

    assign branch_taken = jal || jalr ||
        (branch && (
            (funct3 == 3'b000 && alu_out == 32'd0) ||
            (funct3 == 3'b001 && alu_out != 32'd0)
        ));

    assign branch_target =
    jal  ? (pc + imm) :
    jalr ? ((rs1_val + imm) & 32'hFFFFFFFE) :
    (pc + imm);


    assign alu_b = (alu_src) ? imm : rs2_val;

    logic [31:0] alu_out;

control_unit ctrl_u (
    .opcode(opcode),
    .reg_we(reg_we),
    .alu_src(alu_src),
    .alu_op(alu_op),
    .mem_we(mem_we),
    .mem_re(mem_re),
    .mem_to_reg(mem_to_reg),
    .branch(branch)
);


    dmem dmem(
        .clk(clk),
        .we(mem_we),
        .addr(alu_out),
        .wd(rs2_val),
        .rd(mem_data)
    );

alu_control_unit alu_ctrl_u (
    .alu_op(alu_op),
    .funct3(funct3),
    .funct7(funct7),
    .alu_control(alu_control)
);

    logic [31:0] alu_a;
    assign alu_a = (opcode == 7'b0110111) ? 32'd0 : (opcode == 7'b0010111) ? pc : rs1_val;

    alu alu_u (
        .a(alu_a),
        .b(alu_b),
        .alu_control(alu_control),
        .y(alu_out)
    );

    logic [31:0] rs1_val, rs2_val;
    logic reg_we;

    logic [31:0] writeback_data;
    assign writeback_data =
    (jal || jalr) ? (pc + 32'd4) :
    (mem_to_reg) ? mem_data :
    alu_out;

    regfile rf_u (
        .clk(clk),
         .we(reg_we),
         .rs1(rs1),
         .rs2(rs2),
         .rd(rd),
        .wd(writeback_data),

         .rd1(rs1_val),
         .rd2(rs2_val),
         .dbg_x1(dbg_x1),
        .dbg_x2(dbg_x2),
        .dbg_x3(dbg_x3)
    );


logic [31:0] next_pc;
assign next_pc = branch_taken ? branch_target : (pc + 32'd4);


always @(posedge clk) begin
    cycle++;

    $display("");
    $display("======================================================================");
    $display("                      CYCLE %0d", cycle);
    $display("======================================================================");

    // ---------------- PC ----------------
    $display("PC STAGE");
    $display("  PC (hex) : 0x%08h", pc);
    $display("  PC (dec) : %0d", pc);
    $display("  PC (bin) : %032b", pc);
    $display("");

    // ---------------- FETCH ----------------
    $display("FETCH STAGE");
    $display("  Instruction (hex) : 0x%08h", instr);
    $display("  Instruction (bin) : %032b", instr);
    $display("");

    // ---------------- DECODE ----------------
    $display("DECODE STAGE");
    $display("  opcode : %07b (0x%02h)", opcode, opcode);
    $display("  rd     : x%0d", rd);
    $display("  rs1    : x%0d", rs1);
    $display("  rs2    : x%0d", rs2);
    $display("  funct3 : %03b", funct3);
    $display("  funct7 : %07b", funct7);
    $display("");

    // ---------------- CONTROL ----------------
    $display("CONTROL SIGNALS");
    $display("  reg_we     : %b", reg_we);
    $display("  alu_src    : %b (%s)", 
                alu_src, 
                alu_src ? "Using Immediate" : "Using rs2");
    $display("  alu_op     : %02b", alu_op);
    $display("  alu_ctrl   : %04b (%s)", 
                alu_control, 
                alu_op_name(alu_control));
    $display("");

    // ---------------- REGISTER READ ----------------
    $display("REGISTER FILE READ");
    $display("  rs1 (x%0d) value : %0d (0x%08h) (%032b)", 
                rs1, rs1_val, rs1_val, rs1_val);
    $display("  rs2 (x%0d) value : %0d (0x%08h) (%032b)", 
                rs2, rs2_val, rs2_val, rs2_val); 
    $display("");

    // ---------------- IMMEDIATE ----------------
    $display("IMMEDIATE GENERATOR");
    $display("  imm value : %0d (0x%08h) (%032b)", 
                imm, imm, imm);
    $display("");

    // ---------------- ALU ----------------
    $display("ALU EXECUTION");
    $display("  ALU input A : %0d (0x%08h)", alu_a, alu_a);
    $display("  ALU input B : %0d (0x%08h)", alu_b, alu_b);
    $display("  Operation   : %s", alu_op_name(alu_control));
    $display("  ALU result  : %0d (0x%08h) (%032b)", 
                alu_out, alu_out, alu_out);
    $display("");

    // ---------------- WRITEBACK ----------------
    $display("WRITEBACK STAGE");
    if (reg_we)
        $display("  Writing %0d (0x%08h) to register x%0d",
                writeback_data, writeback_data, rd);
    else
        $display("  No register write this cycle");


    $display("");

    // ---------------- CONTROL FLOW ----------------
    $display("CONTROL FLOW");
    $display("  jal          : %b", jal);
    $display("  jalr         : %b", jalr);
    $display("  branch       : %b", branch);
    $display("  branch_taken : %b", branch_taken);
    $display("  branch_target: 0x%08h", branch_target);
    $display("");

    // ---------------- MEMORY ----------------
    $display("MEMORY STAGE");
    $display("  mem_we     : %b", mem_we);
    $display("  mem_re     : %b", mem_re);
    $display("  mem_to_reg : %b", mem_to_reg);
    $display("  mem_data   : %0d (0x%08h)", mem_data, mem_data);
    $display("");



    // ---------------- REGISTER SNAPSHOT ----------------
    $display("REGISTER SNAPSHOT");
    $display("  x1 : %0d", dbg_x1);
    $display("  x2 : %0d", dbg_x2);
    $display("  x3 : %0d", dbg_x3);

    $display("  Next PC     : %0d ", next_pc);
    $display("======================================================================");
end

endmodule

dump.vcd
$version Generated by VerilatedVcd $end
$date Mon Feb 16 18:20:39 2026
 $end
$timescale   1ps $end

 $scope module TOP $end
  $var wire  1 a clk $end
  $var wire 32 d dbg_x1 [31:0] $end
  $var wire 32 e dbg_x2 [31:0] $end
  $var wire 32 f dbg_x3 [31:0] $end
  $var wire 32 c pc_dbg [31:0] $end
  $var wire  1 b reset $end
  $scope module cpu_top $end
   $var wire 32 ; alu_a [31:0] $end
   $var wire 32 % alu_b [31:0] $end
   $var wire  4 & alu_control [3:0] $end
   $var wire  2 $ alu_op [1:0] $end
   $var wire 32 : alu_out [31:0] $end
   $var wire  1 # alu_src $end
   $var wire  1 3 branch $end
   $var wire  1 4 branch_taken $end
   $var wire 32 5 branch_target [31:0] $end
   $var wire  1 a clk $end
   $var wire 32 6 cycle [31:0] $end
   $var wire 32 d dbg_x1 [31:0] $end
   $var wire 32 e dbg_x2 [31:0] $end
   $var wire 32 f dbg_x3 [31:0] $end
   $var wire  3 - funct3 [2:0] $end
   $var wire  7 . funct7 [6:0] $end
   $var wire 32 7 imm [31:0] $end
   $var wire 32 ( instr [31:0] $end
   $var wire  1 8 jal $end
   $var wire  1 9 jalr $end
   $var wire 32 2 mem_data [31:0] $end
   $var wire  1 0 mem_re $end
   $var wire  1 1 mem_to_reg $end
   $var wire  1 / mem_we $end
   $var wire 32 @ next_pc [31:0] $end
   $var wire  7 ) opcode [6:0] $end
   $var wire 32 ' pc [31:0] $end
   $var wire 32 c pc_dbg [31:0] $end
   $var wire  5 * rd [4:0] $end
   $var wire  1 > reg_we $end
   $var wire  1 b reset $end
   $var wire  5 + rs1 [4:0] $end
   $var wire 32 < rs1_val [31:0] $end
   $var wire  5 , rs2 [4:0] $end
   $var wire 32 = rs2_val [31:0] $end
   $var wire 32 ? writeback_data [31:0] $end
   $scope module alu_ctrl_u $end
    $var wire  4 & alu_control [3:0] $end
    $var wire  2 $ alu_op [1:0] $end
    $var wire  3 - funct3 [2:0] $end
    $var wire  7 . funct7 [6:0] $end
   $upscope $end
   $scope module alu_u $end
    $var wire 32 ; a [31:0] $end
    $var wire  4 & alu_control [3:0] $end
    $var wire 32 % b [31:0] $end
    $var wire 32 : y [31:0] $end
   $upscope $end
   $scope module ctrl_u $end
    $var wire  2 $ alu_op [1:0] $end
    $var wire  1 # alu_src $end
    $var wire  1 3 branch $end
    $var wire  1 0 mem_re $end
    $var wire  1 1 mem_to_reg $end
    $var wire  1 / mem_we $end
    $var wire  7 ) opcode [6:0] $end
    $var wire  1 > reg_we $end
   $upscope $end
   $scope module dec_u $end
    $var wire  3 - funct3 [2:0] $end
    $var wire  7 . funct7 [6:0] $end
    $var wire 32 ( instr [31:0] $end
    $var wire  7 ) opcode [6:0] $end
    $var wire  5 * rd [4:0] $end
    $var wire  5 + rs1 [4:0] $end
    $var wire  5 , rs2 [4:0] $end
   $upscope $end
   $scope module dmem $end
    $var wire 32 : addr [31:0] $end
    $var wire  1 a clk $end
    $var wire 32 2 rd [31:0] $end
    $var wire 32 = wd [31:0] $end
    $var wire  1 / we $end
   $upscope $end
   $scope module imem_u $end
    $var wire 32 ' addr [31:0] $end
    $var wire 32 ( instr [31:0] $end
   $upscope $end
   $scope module imm_u $end
    $var wire 32 7 imm [31:0] $end
    $var wire 32 ( instr [31:0] $end
    $var wire  7 ) opcode [6:0] $end
   $upscope $end
   $scope module pc_u $end
    $var wire  1 4 branch_taken $end
    $var wire 32 5 branch_target [31:0] $end
    $var wire  1 a clk $end
    $var wire 32 ' pc_out [31:0] $end
    $var wire  1 b reset $end
   $upscope $end
   $scope module rf_u $end
    $var wire  1 a clk $end
    $var wire 32 d dbg_x1 [31:0] $end
    $var wire 32 e dbg_x2 [31:0] $end
    $var wire 32 f dbg_x3 [31:0] $end
    $var wire  5 * rd [4:0] $end
    $var wire 32 < rd1 [31:0] $end
    $var wire 32 = rd2 [31:0] $end
    $var wire 32 A regs(0) [31:0] $end
    $var wire 32 B regs(1) [31:0] $end
    $var wire 32 K regs(10) [31:0] $end
    $var wire 32 L regs(11) [31:0] $end
    $var wire 32 M regs(12) [31:0] $end
    $var wire 32 N regs(13) [31:0] $end
    $var wire 32 O regs(14) [31:0] $end
    $var wire 32 P regs(15) [31:0] $end
    $var wire 32 Q regs(16) [31:0] $end
    $var wire 32 R regs(17) [31:0] $end
    $var wire 32 S regs(18) [31:0] $end
    $var wire 32 T regs(19) [31:0] $end
    $var wire 32 C regs(2) [31:0] $end
    $var wire 32 U regs(20) [31:0] $end
    $var wire 32 V regs(21) [31:0] $end
    $var wire 32 W regs(22) [31:0] $end
    $var wire 32 X regs(23) [31:0] $end
    $var wire 32 Y regs(24) [31:0] $end
    $var wire 32 Z regs(25) [31:0] $end
    $var wire 32 [ regs(26) [31:0] $end
    $var wire 32 \ regs(27) [31:0] $end
    $var wire 32 ] regs(28) [31:0] $end
    $var wire 32 ^ regs(29) [31:0] $end
    $var wire 32 D regs(3) [31:0] $end
    $var wire 32 _ regs(30) [31:0] $end
    $var wire 32 ` regs(31) [31:0] $end
    $var wire 32 E regs(4) [31:0] $end
    $var wire 32 F regs(5) [31:0] $end
    $var wire 32 G regs(6) [31:0] $end
    $var wire 32 H regs(7) [31:0] $end
    $var wire 32 I regs(8) [31:0] $end
    $var wire 32 J regs(9) [31:0] $end
    $var wire  5 + rs1 [4:0] $end
    $var wire  5 , rs2 [4:0] $end
    $var wire 32 ? wd [31:0] $end
    $var wire  1 > we $end
   $upscope $end
  $upscope $end
 $upscope $end
$enddefinitions $end


#0
1#
b10 $
b00000000000000000000000000000101 %
b0000 &
b00000000000000000000000000000000 '
b00000000010100000000000010010011 (
b0010011 )
b00001 *
b00000 +
b00101 ,
b000 -
b0000000 .
0/
00
01
b00000000000000000000000000000000 2
03
04
b00000000000000000000000000000101 5
b00000000000000000000000000000000 6
b00000000000000000000000000000101 7
08
09
b00000000000000000000000000000101 :
b00000000000000000000000000000000 ;
b00000000000000000000000000000000 <
b00000000000000000000000000000000 =
1>
b00000000000000000000000000000101 ?
b00000000000000000000000000000100 @
b00000000000000000000000000000000 A
b00000000000000000000000000000000 B
b00000000000000000000000000000000 C
b00000000000000000000000000000000 D
b00000000000000000000000000000000 E
b00000000000000000000000000000000 F
b00000000000000000000000000000000 G
b00000000000000000000000000000000 H
b00000000000000000000000000000000 I
b00000000000000000000000000000000 J
b00000000000000000000000000000000 K
b00000000000000000000000000000000 L
b00000000000000000000000000000000 M
b00000000000000000000000000000000 N
b00000000000000000000000000000000 O
b00000000000000000000000000000000 P
b00000000000000000000000000000000 Q
b00000000000000000000000000000000 R
b00000000000000000000000000000000 S
b00000000000000000000000000000000 T
b00000000000000000000000000000000 U
b00000000000000000000000000000000 V
b00000000000000000000000000000000 W
b00000000000000000000000000000000 X
b00000000000000000000000000000000 Y
b00000000000000000000000000000000 Z
b00000000000000000000000000000000 [
b00000000000000000000000000000000 \
b00000000000000000000000000000000 ]
b00000000000000000000000000000000 ^
b00000000000000000000000000000000 _
b00000000000000000000000000000000 `
1a
1b
b00000000000000000000000000000000 c
b00000000000000000000000000000000 d
b00000000000000000000000000000000 e
b00000000000000000000000000000000 f
#1
0a
#2
b00000000000000000000000000001000 %
b00000000000000000000000000000100 '
b00000000100000000000001011101111 (
b1101111 )
b00101 *
b01000 ,
14
b00000000000000000000000000001100 5
b00000000000000000000000000000001 6
b00000000000000000000000000001000 7
18
b00000000000000000000000000001000 :
b00000000000000000000000000001000 ?
b00000000000000000000000000001100 @
b00000000000000000000000000000101 B
1a
0b
b00000000000000000000000000000100 c
b00000000000000000000000000000101 d
#3
0a
#4
b00000000000000000000000000001010 %
b00000000000000000000000000001100 '
b00000000101000001000000010010011 (
b0010011 )
b00001 *
b00001 +
b01010 ,
04
b00000000000000000000000000010110 5
b00000000000000000000000000000010 6
b00000000000000000000000000001010 7
08
b00000000000000000000000000001111 :
b00000000000000000000000000000101 ;
b00000000000000000000000000000101 <
b00000000000000000000000000001111 ?
b00000000000000000000000000010000 @
b00000000000000000000000000001000 F
1a
b00000000000000000000000000001100 c
#5
0a
#6
b00000000000000000000000000000000 %
b00000000000000000000000000010000 '
b00000000000000101000000001100111 (
b1100111 )
b00000 *
b00101 +
b00000 ,
14
b00000000000000000000000000001000 5
b00000000000000000000000000000011 6
b00000000000000000000000000000000 7
19
b00000000000000000000000000001000 :
b00000000000000000000000000001000 ;
b00000000000000000000000000001000 <
b00000000000000000000000000010100 ?
b00000000000000000000000000001000 @
b00000000000000000000000000001111 B
1a
b00000000000000000000000000010000 c
b00000000000000000000000000001111 d
#7
0a
#8
b00000000000000000000000000001000 '
b00000000000000000000000001101111 (
b1101111 )
b00000 +
b00000000000000000000000000000100 6
18
09
b00000000000000000000000000000000 :
b00000000000000000000000000000000 ;
b00000000000000000000000000000000 <
b00000000000000000000000000001100 ?
1a
b00000000000000000000000000001000 c
#9
0a
#10
b00000000000000000000000000000101 6
1a
#11
0a
#12
b00000000000000000000000000000110 6
1a
#13
0a
#14
b00000000000000000000000000000111 6
1a
#15
0a
#16
b00000000000000000000000000001000 6
1a
#17
0a
#18
b00000000000000000000000000001001 6
1a
#19
0a
#20
b00000000000000000000000000001010 6
1a
#21
0a
#22
b00000000000000000000000000001011 6
1a
#23
0a
#24
b00000000000000000000000000001100 6
1a
#25
0a
#26
b00000000000000000000000000001101 6
1a
#27
0a
#28
b00000000000000000000000000001110 6
1a
#29
0a
#30
b00000000000000000000000000001111 6
1a
#31
0a
#32
b00000000000000000000000000010000 6
1a
#33
0a
#34
b00000000000000000000000000010001 6
1a
#35
0a
#36
b00000000000000000000000000010010 6
1a
#37
0a
#38
b00000000000000000000000000010011 6
1a
#39
0a
#40
b00000000000000000000000000010100 6
1a
#41
0a
#42
b00000000000000000000000000010101 6
1a
#43
0a
#44
b00000000000000000000000000010110 6
1a
#45
0a
#46
b00000000000000000000000000010111 6
1a
#47
0a
#48
b00000000000000000000000000011000 6
1a
#49
0a
#50
b00000000000000000000000000011001 6
1a
#51
0a
#52
b00000000000000000000000000011010 6
1a
#53
0a
#54
b00000000000000000000000000011011 6
1a
#55
0a
#56
b00000000000000000000000000011100 6
1a
#57
0a
#58
b00000000000000000000000000011101 6
1a
#59
0a
#60
b00000000000000000000000000011110 6
1a
#61
0a
#62
b00000000000000000000000000011111 6
1a
#63
0a
#64
b00000000000000000000000000100000 6
1a
#65
0a
#66
b00000000000000000000000000100001 6
1a
#67
0a
#68
b00000000000000000000000000100010 6
1a
#69
0a
#70
b00000000000000000000000000100011 6
1a
#71
0a
#72
b00000000000000000000000000100100 6
1a
#73
0a
#74
b00000000000000000000000000100101 6
1a
#75
0a
#76
b00000000000000000000000000100110 6
1a
#77
0a
#78
b00000000000000000000000000100111 6
1a
#79
0a
#80
b00000000000000000000000000101000 6
1a
#81
0a
#82
b00000000000000000000000000101001 6
1a
#83
0a
#84
b00000000000000000000000000101010 6
1a
#85
0a
#86
b00000000000000000000000000101011 6
1a
#87
0a
#88
b00000000000000000000000000101100 6
1a
#89
0a
#90
b00000000000000000000000000101101 6
1a
#91
0a
#92
b00000000000000000000000000101110 6
1a
#93
0a
#94
b00000000000000000000000000101111 6
1a
#95
0a
#96
b00000000000000000000000000110000 6
1a
#97
0a
#98
b00000000000000000000000000110001 6
1a
#99
0a
#100
b00000000000000000000000000110010 6
1a
#101
0a
#102
b00000000000000000000000000110011 6
1a
#103
0a
#104
b00000000000000000000000000110100 6
1a
#105
0a
#106
b00000000000000000000000000110101 6
1a
#107
0a
#108
b00000000000000000000000000110110 6
1a
#109
0a
#110
b00000000000000000000000000110111 6
1a
#111
0a
#112
b00000000000000000000000000111000 6
1a
#113
0a
#114
b00000000000000000000000000111001 6
1a
#115
0a
#116
b00000000000000000000000000111010 6
1a
#117
0a
#118
b00000000000000000000000000111011 6
1a
#119
0a
#120
b00000000000000000000000000111100 6
1a
#121
0a
#122
b00000000000000000000000000111101 6
1a
#123
0a
#124
b00000000000000000000000000111110 6
1a
#125
0a
#126
b00000000000000000000000000111111 6
1a
#127
0a
#128
b00000000000000000000000001000000 6
1a
#129
0a
#130
b00000000000000000000000001000001 6
1a
#131
0a
#132
b00000000000000000000000001000010 6
1a
#133
0a
#134
b00000000000000000000000001000011 6
1a
#135
0a
#136
b00000000000000000000000001000100 6
1a
#137
0a
#138
b00000000000000000000000001000101 6
1a
#139
0a
#140
b00000000000000000000000001000110 6
1a
#141
0a
#142
b00000000000000000000000001000111 6
1a
#143
0a
#144
b00000000000000000000000001001000 6
1a
#145
0a
#146
b00000000000000000000000001001001 6
1a
#147
0a
#148
b00000000000000000000000001001010 6
1a
#149
0a
#150
b00000000000000000000000001001011 6
1a
#151
0a
