rtl/regfile.sv
// the special file where the outputs from the decoder are sent.

module regfile (
    input logic clk,
    input logic we, // safety switch write enable, 0 or 1.

    input logic [4:0] rs1, // decoder sends rs1 and rs2, the numbers CPU has to grab and send to ALU.
    input logic [4:0] rs2,
    input logic [4:0] rd, // recieved by the decoder
    input logic [31:0] wd, // comes from the ALU, is 32 bit. write data.
    output logic [31:0] rd1,
    output logic [31:0] rd2,
    output logic [31:0] dbg_x1,
    output logic [31:0] dbg_x2,
    output logic [31:0] dbg_x3
);

    logic [31:0] regs [0:31]; // 32 registers, each 32 bits wide

    // 32'd0 = 32 bit wide decimal zero

    assign rd1 = (rs1 == 0) ? 32'd0 : regs[rs1]; // checks if the given register is zero, if yes, then it returns 32 bit wide zero, else it returns the value of the register.
    assign rd2 = (rs2 == 0) ? 32'd0 : regs[rs2];
    assign dbg_x1 = regs[1];
    assign dbg_x2 = regs[2];
    assign dbg_x3 = regs[3];

    always_ff @(posedge clk) begin // waiting for the clock, only then we right. so that the voltage gets on 1.
        if (we && rd != 0)
            regs[rd] <= wd;
    end

endmodule

rtl/alu.sv
// simple alu, only adds for now

module alu (
    input  logic [31:0] a,
    input  logic [31:0] b,
    output logic [31:0] y
);

    assign y = a + b; 

endmodule

rtl/imm_gen.sv
module imm_gen (
    input logic [31:0] instr,
    output logic [31:0] imm
);


    // this is sent to the ALU. This extracts the immediate value from the instruction. 
    assign imm = {{20{instr[31]}}, instr[31:20]};

endmodule

rtl/decoder.sv
// general logic decoder is what takes a binary number, and turns it into a signal. A single signal.
// and this decoder, is an instruction decoder. which takes a big chunk of machine code, splits it into smaller pieces and sends it to the CPU to allocate regsters.

module decoder (
    
    input logic [31:0] instr, // The output instruction which we sent from our memory module, ROM.
    output logic [6:0] opcode, // tells the CPU which type of instruction it is, 7 bits wide.
    output logic [4:0] rd, // the desintation register, the place where the result of the opcode instruction will be stored.
    output logic [4:0] rs1, // source register 1, the two numbers which CPU will grab to sent to the ALU.
    output logic [4:0] rs2, // source register 2
    output logic [2:0] funct3, // some extra bits used to distniguish further between instructions.
    output logic [6:0] funct7
   
);

// this part splits the instruction.
// lets say, the instr is 000000 00010 00001 000 00011 0110011
// opcode = 0110011
// rd = 00011
// funct3 = 000
// rs1 = 00001
// rs2 = 00010
// funct7 = 000000

    assign opcode = instr[6:0];
    assign rd = instr[11:7];
    assign funct3 = instr[14:12];
    assign rs1 = instr[19:15];
    assign rs2 = instr[24:20];
    assign funct7 = instr[31:25];


endmodule

rtl/imem.sv
module imem (
    input logic [31:0] addr, // the address of the instruction
    output logic [31:0] instr // the 32 bit instruction, which is returned
);

    logic [31:0] mem [0:255]; // this is the storage of memory, has 256 slots, and each slot is 32 bits wide. It can hold 256 instructions.

    initial begin 
        // These are the list of pre-loaded instructions right now.
        // 32'h00000013 = NOP (no operation, do nothing, for now)
       // mem[0] = 32'h00000013; 
        //mem[1] = 32'h00000013;
        //mem[2] = 32'h00000013;
        mem[0] = 32'h00500093; // addi x1, x0, 5
        mem[1] = 32'h00308113; // addi x2, x1, 3
        mem[2] = 32'h00210193; // addi x3, x2, 2
    end

    // in 32 bit systems, instructions are 4 bytes long, so each instruction takes 4 bytes. here mem[0] is on address 0, but mem[1] is on address 4 and mem[2] is on address 8.
    // so as the instruction is 4 bytes long, the end of it's binary address is with 00. so we're simply stripping off the last two 0s in this code.
    // this simply divides the address by 4. This is the bit shift, shifting right side by two places.
    // 9 is the ceiling because from n power of 2, the maximum it could go is 8. 8 bits, but only for the 256 slots we assigned.
    assign instr = mem[addr[9:2]]; // finally assigning the output instruction which was 32 bits wide, 

endmodule

rtl/pc.sv
// Program Counter (PC) Module
// This holds the memory address of the next instructino, represented by numbers here 1-4
// This module increments the program counter by 4 on each clock cycle.
// It resets to 0 when the reset signal is high.
// The limit of the pc_out is 32 bits.

module pc (
    input logic clk, 
    input logic reset, 
    output logic [31:0] pc_out
); 

    always_ff @(posedge clk) begin 
        if (reset)
            pc_out <= 32'd0;
        else 
            pc_out <= pc_out + 32'd4; // 32'd4 = 4
    end

endmodule

rtl/cpu_top.sv
module cpu_top (
    input  logic clk,
    input  logic reset,
    output logic [31:0] pc_dbg,
    output logic [31:0] dbg_x1,
    output logic [31:0] dbg_x2,
    output logic [31:0] dbg_x3
);

    logic [31:0] pc; // program counter
    logic [31:0] instr; // instructions
    assign pc_dbg = pc;
    logic [6:0] opcode; // type of instruction
    logic [4:0] rd, rs1, rs2;// the register destination and sources
    logic [2:0] funct3; // extra bits to distinguish between instructions
    logic [6:0] funct7; // extra bits to distinguish between instructions

    pc pc_u (
        .clk(clk),
        .reset(reset),
        .pc_out(pc)
    );

    imem imem_u (
        .addr(pc), 
        .instr(instr) // returns 000000 00010 00001 000 00011 0110011
    );

    decoder dec_u (
        .instr(instr),
        .opcode(opcode),
        .rd(rd),
        .rs1(rs1),
        .rs2(rs2),
        .funct3(funct3),
        .funct7(funct7)
    );

    logic [31:0] imm;

    imm_gen imm_u (
        .instr(instr),
        .imm(imm)
    );

    logic [31:0] alu_out;

    alu alu_u (
        .a(rs1_val),
        .b(imm),
        .y(alu_out)
    );

    logic [31:0] rs1_val, rs2_val;
    logic reg_we;

    regfile rf_u (
        .clk(clk),
         .we(reg_we),
         .rs1(rs1),
         .rs2(rs2),
         .rd(rd),
         .wd(alu_out),
         .rd1(rs1_val),
         .rd2(rs2_val),
         .dbg_x1(dbg_x1),
        .dbg_x2(dbg_x2),
        .dbg_x3(dbg_x3)
    );

    always_comb begin 
        reg_we = 1'b0;

        if (opcode == 7'b0010011) 
            reg_we = 1'b1;
    end

// pc sends data -> sends that to imem to store -> then imem sends to decoder 

//PC updates (on clock edge)
//        ↓
//pc wire changes
//        ↓
//imem sees new addr
//        ↓
//instr wire changes
//        ↓
//decoder outputs change
//        ↓
//everything settles


// From the second update after I added ALU, regfile and the imm logic,
// firstly the program counter starts at 0 then points to imem,
// that at address 0 the machine code is 0000011012 etc. and that is the instruction which is returned by the imem.
// After that the instruction is sent to the decoder, which mainly returns rs1 and opcode respectively
// for regfile and ALU. the rs1 and rs2 are the register sources. Meanwhile the imm_gen extracts the constant number, the imm, from that instruction.
// Then the regfile takes the rs1 and rs2 and returns the values of those registers, rs1_val and rs2_val.
// Then the ALU takes the rs1_val and imm and returns the result of the operation.
// the always_comb block checks for the write enable safety switch. if the instruction is supposed to save a result.

// So, let's say the regfile give sthe value for rs1 as 5, and the imm generates the value as 10 so its sent to the ALU and ALU just does y = a + b
// which is 15 on the alu_out wire. The regfile then sees that we is 1
// so the switch for writing is on, it checks the value of alu_out and then it writes it into the rd, taking value from the wd. 
// which gives us dbg_x1 as 15. dbg_x2 and x3 are simply the other registers.



endmodule

dump.vcd
$version Generated by VerilatedVcd $end
$date Thu Feb  5 11:13:28 2026
 $end
$timescale   1ps $end

 $scope module TOP $end
  $var wire  1 P clk $end
  $var wire 32 S dbg_x1 [31:0] $end
  $var wire 32 T dbg_x2 [31:0] $end
  $var wire 32 U dbg_x3 [31:0] $end
  $var wire 32 R pc_dbg [31:0] $end
  $var wire  1 Q reset $end
  $scope module cpu_top $end
   $var wire 32 , alu_out [31:0] $end
   $var wire  1 P clk $end
   $var wire 32 S dbg_x1 [31:0] $end
   $var wire 32 T dbg_x2 [31:0] $end
   $var wire 32 U dbg_x3 [31:0] $end
   $var wire  3 ) funct3 [2:0] $end
   $var wire  7 * funct7 [6:0] $end
   $var wire 32 + imm [31:0] $end
   $var wire 32 $ instr [31:0] $end
   $var wire  7 % opcode [6:0] $end
   $var wire 32 # pc [31:0] $end
   $var wire 32 R pc_dbg [31:0] $end
   $var wire  5 & rd [4:0] $end
   $var wire  1 / reg_we $end
   $var wire  1 Q reset $end
   $var wire  5 ' rs1 [4:0] $end
   $var wire 32 - rs1_val [31:0] $end
   $var wire  5 ( rs2 [4:0] $end
   $var wire 32 . rs2_val [31:0] $end
   $scope module alu_u $end
    $var wire 32 - a [31:0] $end
    $var wire 32 + b [31:0] $end
    $var wire 32 , y [31:0] $end
   $upscope $end
   $scope module dec_u $end
    $var wire  3 ) funct3 [2:0] $end
    $var wire  7 * funct7 [6:0] $end
    $var wire 32 $ instr [31:0] $end
    $var wire  7 % opcode [6:0] $end
    $var wire  5 & rd [4:0] $end
    $var wire  5 ' rs1 [4:0] $end
    $var wire  5 ( rs2 [4:0] $end
   $upscope $end
   $scope module imem_u $end
    $var wire 32 # addr [31:0] $end
    $var wire 32 $ instr [31:0] $end
   $upscope $end
   $scope module imm_u $end
    $var wire 32 + imm [31:0] $end
    $var wire 32 $ instr [31:0] $end
   $upscope $end
   $scope module pc_u $end
    $var wire  1 P clk $end
    $var wire 32 # pc_out [31:0] $end
    $var wire  1 Q reset $end
   $upscope $end
   $scope module rf_u $end
    $var wire  1 P clk $end
    $var wire 32 S dbg_x1 [31:0] $end
    $var wire 32 T dbg_x2 [31:0] $end
    $var wire 32 U dbg_x3 [31:0] $end
    $var wire  5 & rd [4:0] $end
    $var wire 32 - rd1 [31:0] $end
    $var wire 32 . rd2 [31:0] $end
    $var wire 32 0 regs(0) [31:0] $end
    $var wire 32 1 regs(1) [31:0] $end
    $var wire 32 : regs(10) [31:0] $end
    $var wire 32 ; regs(11) [31:0] $end
    $var wire 32 < regs(12) [31:0] $end
    $var wire 32 = regs(13) [31:0] $end
    $var wire 32 > regs(14) [31:0] $end
    $var wire 32 ? regs(15) [31:0] $end
    $var wire 32 @ regs(16) [31:0] $end
    $var wire 32 A regs(17) [31:0] $end
    $var wire 32 B regs(18) [31:0] $end
    $var wire 32 C regs(19) [31:0] $end
    $var wire 32 2 regs(2) [31:0] $end
    $var wire 32 D regs(20) [31:0] $end
    $var wire 32 E regs(21) [31:0] $end
    $var wire 32 F regs(22) [31:0] $end
    $var wire 32 G regs(23) [31:0] $end
    $var wire 32 H regs(24) [31:0] $end
    $var wire 32 I regs(25) [31:0] $end
    $var wire 32 J regs(26) [31:0] $end
    $var wire 32 K regs(27) [31:0] $end
    $var wire 32 L regs(28) [31:0] $end
    $var wire 32 M regs(29) [31:0] $end
    $var wire 32 3 regs(3) [31:0] $end
    $var wire 32 N regs(30) [31:0] $end
    $var wire 32 O regs(31) [31:0] $end
    $var wire 32 4 regs(4) [31:0] $end
    $var wire 32 5 regs(5) [31:0] $end
    $var wire 32 6 regs(6) [31:0] $end
    $var wire 32 7 regs(7) [31:0] $end
    $var wire 32 8 regs(8) [31:0] $end
    $var wire 32 9 regs(9) [31:0] $end
    $var wire  5 ' rs1 [4:0] $end
    $var wire  5 ( rs2 [4:0] $end
    $var wire 32 , wd [31:0] $end
    $var wire  1 / we $end
   $upscope $end
  $upscope $end
 $upscope $end
$enddefinitions $end


#0
b00000000000000000000000000000000 #
b00000000010100000000000010010011 $
b0010011 %
b00001 &
b00000 '
b00101 (
b000 )
b0000000 *
b00000000000000000000000000000101 +
b00000000000000000000000000000101 ,
b00000000000000000000000000000000 -
b00000000000000000000000000000000 .
1/
b00000000000000000000000000000000 0
b00000000000000000000000000000000 1
b00000000000000000000000000000000 2
b00000000000000000000000000000000 3
b00000000000000000000000000000000 4
b00000000000000000000000000000000 5
b00000000000000000000000000000000 6
b00000000000000000000000000000000 7
b00000000000000000000000000000000 8
b00000000000000000000000000000000 9
b00000000000000000000000000000000 :
b00000000000000000000000000000000 ;
b00000000000000000000000000000000 <
b00000000000000000000000000000000 =
b00000000000000000000000000000000 >
b00000000000000000000000000000000 ?
b00000000000000000000000000000000 @
b00000000000000000000000000000000 A
b00000000000000000000000000000000 B
b00000000000000000000000000000000 C
b00000000000000000000000000000000 D
b00000000000000000000000000000000 E
b00000000000000000000000000000000 F
b00000000000000000000000000000000 G
b00000000000000000000000000000000 H
b00000000000000000000000000000000 I
b00000000000000000000000000000000 J
b00000000000000000000000000000000 K
b00000000000000000000000000000000 L
b00000000000000000000000000000000 M
b00000000000000000000000000000000 N
b00000000000000000000000000000000 O
1P
1Q
b00000000000000000000000000000000 R
b00000000000000000000000000000000 S
b00000000000000000000000000000000 T
b00000000000000000000000000000000 U
#1
0P
#2
b00000000000000000000000000000100 #
b00000000001100001000000100010011 $
b00010 &
b00001 '
b00011 (
b00000000000000000000000000000011 +
b00000000000000000000000000001000 ,
b00000000000000000000000000000101 -
b00000000000000000000000000000101 1
1P
0Q
b00000000000000000000000000000100 R
b00000000000000000000000000000101 S
#3
0P
#4
b00000000000000000000000000001000 #
b00000000001000010000000110010011 $
b00011 &
b00010 '
b00010 (
b00000000000000000000000000000010 +
b00000000000000000000000000001010 ,
b00000000000000000000000000001000 -
b00000000000000000000000000001000 .
b00000000000000000000000000001000 2
1P
b00000000000000000000000000001000 R
b00000000000000000000000000001000 T
#5
0P
#6
b00000000000000000000000000001100 #
b00000000000000000000000000000000 $
b0000000 %
b00000 &
b00000 '
b00000 (
b00000000000000000000000000000000 +
b00000000000000000000000000000000 ,
b00000000000000000000000000000000 -
b00000000000000000000000000000000 .
0/
b00000000000000000000000000001010 3
1P
b00000000000000000000000000001100 R
b00000000000000000000000000001010 U
#7
0P
#8
b00000000000000000000000000010000 #
1P
b00000000000000000000000000010000 R
#9
0P
#10
b00000000000000000000000000010100 #
1P
b00000000000000000000000000010100 R
#11
0P
#12
b00000000000000000000000000011000 #
1P
b00000000000000000000000000011000 R
#13
0P
#14
b00000000000000000000000000011100 #
1P
b00000000000000000000000000011100 R
#15
0P
#16
b00000000000000000000000000100000 #
1P
b00000000000000000000000000100000 R
#17
0P
#18
b00000000000000000000000000100100 #
1P
b00000000000000000000000000100100 R
#19
0P
#20
b00000000000000000000000000101000 #
1P
b00000000000000000000000000101000 R
#21
0P
#22
b00000000000000000000000000101100 #
1P
b00000000000000000000000000101100 R
#23
0P
#24
b00000000000000000000000000110000 #
1P
b00000000000000000000000000110000 R
#25
0P
#26
b00000000000000000000000000110100 #
1P
b00000000000000000000000000110100 R
#27
0P
#28
b00000000000000000000000000111000 #
1P
b00000000000000000000000000111000 R
#29
0P
#30
b00000000000000000000000000111100 #
1P
b00000000000000000000000000111100 R
#31
0P
#32
b00000000000000000000000001000000 #
1P
b00000000000000000000000001000000 R
#33
0P
#34
b00000000000000000000000001000100 #
1P
b00000000000000000000000001000100 R
#35
0P
#36
b00000000000000000000000001001000 #
1P
b00000000000000000000000001001000 R
#37
0P
#38
b00000000000000000000000001001100 #
1P
b00000000000000000000000001001100 R
#39
0P
#40
b00000000000000000000000001010000 #
1P
b00000000000000000000000001010000 R
#41
0P
#42
b00000000000000000000000001010100 #
1P
b00000000000000000000000001010100 R
#43
0P
#44
b00000000000000000000000001011000 #
1P
b00000000000000000000000001011000 R
#45
0P
#46
b00000000000000000000000001011100 #
1P
b00000000000000000000000001011100 R
#47
0P
#48
b00000000000000000000000001100000 #
1P
b00000000000000000000000001100000 R
#49
0P
#50
b00000000000000000000000001100100 #
1P
b00000000000000000000000001100100 R
#51
0P
#52
b00000000000000000000000001101000 #
1P
b00000000000000000000000001101000 R
#53
0P
#54
b00000000000000000000000001101100 #
1P
b00000000000000000000000001101100 R
#55
0P
#56
b00000000000000000000000001110000 #
1P
b00000000000000000000000001110000 R
#57
0P
#58
b00000000000000000000000001110100 #
1P
b00000000000000000000000001110100 R
#59
0P
#60
b00000000000000000000000001111000 #
1P
b00000000000000000000000001111000 R
#61
0P
#62
b00000000000000000000000001111100 #
1P
b00000000000000000000000001111100 R
#63
0P
#64
b00000000000000000000000010000000 #
1P
b00000000000000000000000010000000 R
#65
0P
#66
b00000000000000000000000010000100 #
1P
b00000000000000000000000010000100 R
#67
0P
#68
b00000000000000000000000010001000 #
1P
b00000000000000000000000010001000 R
#69
0P
#70
b00000000000000000000000010001100 #
1P
b00000000000000000000000010001100 R
#71
0P
#72
b00000000000000000000000010010000 #
1P
b00000000000000000000000010010000 R
#73
0P
#74
b00000000000000000000000010010100 #
1P
b00000000000000000000000010010100 R
#75
0P
#76
b00000000000000000000000010011000 #
1P
b00000000000000000000000010011000 R
#77
0P
#78
b00000000000000000000000010011100 #
1P
b00000000000000000000000010011100 R
#79
0P
#80
b00000000000000000000000010100000 #
1P
b00000000000000000000000010100000 R
#81
0P
#82
b00000000000000000000000010100100 #
1P
b00000000000000000000000010100100 R
#83
0P
#84
b00000000000000000000000010101000 #
1P
b00000000000000000000000010101000 R
#85
0P
#86
b00000000000000000000000010101100 #
1P
b00000000000000000000000010101100 R
#87
0P
#88
b00000000000000000000000010110000 #
1P
b00000000000000000000000010110000 R
#89
0P
#90
b00000000000000000000000010110100 #
1P
b00000000000000000000000010110100 R
#91
0P
#92
b00000000000000000000000010111000 #
1P
b00000000000000000000000010111000 R
#93
0P
#94
b00000000000000000000000010111100 #
1P
b00000000000000000000000010111100 R
#95
0P
#96
b00000000000000000000000011000000 #
1P
b00000000000000000000000011000000 R
#97
0P
#98
b00000000000000000000000011000100 #
1P
b00000000000000000000000011000100 R
